twintradeai
